{
    "version": "5.0.1",
    "flags": {},
    "shapes": [
        {
            "label": "Con_Casco",
            "points": [
                [
                    45.31488000000002,
                    9.789119999999997
                ],
                [
                    349.77632,
                    408.68128
                ]
            ],
            "group_id": null,
            "shape_type": "rectangle",
            "flags": {}
        }
    ],
    "imagePath": "1009_aug2.jpg",
    "imageData": null,
    "imageHeight": 640,
    "imageWidth": 640
}