{
    "version": "5.0.1",
    "flags": {},
    "shapes": [
        {
            "label": "Con_Casco",
            "points": [
                [
                    364.7504,
                    95.0
                ],
                [
                    489.25023999999996,
                    353.0
                ]
            ],
            "group_id": null,
            "shape_type": "rectangle",
            "flags": {}
        },
        {
            "label": "Con_Casco",
            "points": [
                [
                    202.75039999999998,
                    89.75008000000001
                ],
                [
                    315.25023999999996,
                    329.25024
                ]
            ],
            "group_id": null,
            "shape_type": "rectangle",
            "flags": {}
        }
    ],
    "imagePath": "100_aug2.jpg",
    "imageData": null,
    "imageHeight": 640,
    "imageWidth": 640
}