{
    "version": "5.0.1",
    "flags": {},
    "shapes": [
        {
            "label": "Sin_Casco_Mascarrilla",
            "points": [
                [
                    396.0,
                    134.75008000000003
                ],
                [
                    443.00032,
                    264.25024
                ]
            ],
            "group_id": null,
            "shape_type": "rectangle",
            "flags": {}
        },
        {
            "label": "Sin_Casco_Mascarrilla",
            "points": [
                [
                    561.50016,
                    225.74976
                ],
                [
                    621.50016,
                    375.24992
                ]
            ],
            "group_id": null,
            "shape_type": "rectangle",
            "flags": {}
        },
        {
            "label": "Con_Casco",
            "points": [
                [
                    277.25023999999996,
                    103.50016
                ],
                [
                    376.7504,
                    227.50016
                ]
            ],
            "group_id": null,
            "shape_type": "rectangle",
            "flags": {}
        }
    ],
    "imagePath": "1072_aug1.jpg",
    "imageData": null,
    "imageHeight": 640,
    "imageWidth": 640
}