{
    "version": "5.0.1",
    "flags": {},
    "shapes": [
        {
            "label": "Sin_Casco_Mascarrilla",
            "points": [
                [
                    279.75007999999997,
                    286.74976
                ],
                [
                    307.25024,
                    338.24992000000003
                ]
            ],
            "group_id": null,
            "shape_type": "rectangle",
            "flags": {}
        },
        {
            "label": "Sin_Casco_Mascarrilla",
            "points": [
                [
                    399.99968,
                    273.2496
                ],
                [
                    425.99968,
                    312.74976000000004
                ]
            ],
            "group_id": null,
            "shape_type": "rectangle",
            "flags": {}
        },
        {
            "label": "Sin_Casco_Mascarrilla",
            "points": [
                [
                    141.24992,
                    303.50016
                ],
                [
                    171.74976,
                    355.50016
                ]
            ],
            "group_id": null,
            "shape_type": "rectangle",
            "flags": {}
        },
        {
            "label": "Sin_Casco_Mascarrilla",
            "points": [
                [
                    200.74976,
                    271.0
                ],
                [
                    225.24960000000002,
                    321.0
                ]
            ],
            "group_id": null,
            "shape_type": "rectangle",
            "flags": {}
        },
        {
            "label": "Con_Chaleco",
            "points": [
                [
                    72.24991999999999,
                    301.0
                ],
                [
                    104.74976,
                    371.0
                ]
            ],
            "group_id": null,
            "shape_type": "rectangle",
            "flags": {}
        },
        {
            "label": "Sin_Chaleco",
            "points": [
                [
                    272.00032,
                    340.7497599999999
                ],
                [
                    310.00032,
                    441.2496
                ]
            ],
            "group_id": null,
            "shape_type": "rectangle",
            "flags": {}
        },
        {
            "label": "Sin_Chaleco",
            "points": [
                [
                    401.00000000000006,
                    317.99967999999996
                ],
                [
                    434.00032000000004,
                    403.99967999999996
                ]
            ],
            "group_id": null,
            "shape_type": "rectangle",
            "flags": {}
        }
    ],
    "imagePath": "1090_aug2.jpg",
    "imageData": null,
    "imageHeight": 640,
    "imageWidth": 640
}