{
    "version": "5.0.1",
    "flags": {},
    "shapes": [
        {
            "label": "Con_Chaleco",
            "points": [
                [
                    52.75008000000001,
                    384.49983999999995
                ],
                [
                    98.25024,
                    520.49984
                ]
            ],
            "group_id": null,
            "shape_type": "rectangle",
            "flags": {}
        },
        {
            "label": "Con_Chaleco",
            "points": [
                [
                    358.0,
                    131.24992
                ],
                [
                    390.0,
                    200.75008
                ]
            ],
            "group_id": null,
            "shape_type": "rectangle",
            "flags": {}
        }
    ],
    "imagePath": "1157_aug3.jpg",
    "imageData": null,
    "imageHeight": 640,
    "imageWidth": 640
}