{
    "version": "5.0.1",
    "flags": {},
    "shapes": [
        {
            "label": "Con_Chaleco",
            "points": [
                [
                    261.0,
                    221.99967999999996
                ],
                [
                    555.0,
                    639.9996799999999
                ]
            ],
            "group_id": null,
            "shape_type": "rectangle",
            "flags": {}
        },
        {
            "label": "Con_Casco",
            "points": [
                [
                    392.00032,
                    45.499840000000006
                ],
                [
                    562.00032,
                    263.49984
                ]
            ],
            "group_id": null,
            "shape_type": "rectangle",
            "flags": {}
        }
    ],
    "imagePath": "1411_aug2.jpg",
    "imageData": null,
    "imageHeight": 640,
    "imageWidth": 640
}