{
    "version": "5.0.1",
    "flags": {},
    "shapes": [
        {
            "label": "Sin_Chaleco",
            "points": [
                [
                    177.75008,
                    238.24959999999996
                ],
                [
                    506.24992,
                    623.7497599999999
                ]
            ],
            "group_id": null,
            "shape_type": "rectangle",
            "flags": {}
        },
        {
            "label": "Sin_Casco_Mascarrilla",
            "points": [
                [
                    245.75008,
                    10.750079999999997
                ],
                [
                    418.24992,
                    233.24992
                ]
            ],
            "group_id": null,
            "shape_type": "rectangle",
            "flags": {}
        }
    ],
    "imagePath": "1646_aug3.jpg",
    "imageData": null,
    "imageHeight": 640,
    "imageWidth": 640
}