{
    "version": "5.0.1",
    "flags": {},
    "shapes": [
        {
            "label": "Sin_Casco_Mascarrilla",
            "points": [
                [
                    214.50016,
                    74.24960000000002
                ],
                [
                    388.50016,
                    291.74976000000004
                ]
            ],
            "group_id": null,
            "shape_type": "rectangle",
            "flags": {}
        },
        {
            "label": "Con_Chaleco",
            "points": [
                [
                    152.0,
                    303.00032
                ],
                [
                    507.00032,
                    640.0
                ]
            ],
            "group_id": null,
            "shape_type": "rectangle",
            "flags": {}
        }
    ],
    "imagePath": "1650_aug1.jpg",
    "imageData": null,
    "imageHeight": 640,
    "imageWidth": 640
}