{
    "version": "5.0.1",
    "flags": {},
    "shapes": [
        {
            "label": "Sin_Casco_Mascarrilla",
            "points": [
                [
                    361.93567999999993,
                    0.0
                ],
                [
                    483.31615999999997,
                    98.0864
                ]
            ],
            "group_id": null,
            "shape_type": "rectangle",
            "flags": {}
        },
        {
            "label": "Sin_Casco_Mascarrilla",
            "points": [
                [
                    159.72415999999998,
                    51.79647999999999
                ],
                [
                    250.16768000000002,
                    195.47776
                ]
            ],
            "group_id": null,
            "shape_type": "rectangle",
            "flags": {}
        },
        {
            "label": "Sin_Chaleco",
            "points": [
                [
                    106.82816,
                    181.51328
                ],
                [
                    317.33439999999996,
                    551.62208
                ]
            ],
            "group_id": null,
            "shape_type": "rectangle",
            "flags": {}
        }
    ],
    "imagePath": "1653_aug3.jpg",
    "imageData": null,
    "imageHeight": 640,
    "imageWidth": 640
}