{
    "version": "5.0.1",
    "flags": {},
    "shapes": [
        {
            "label": "Con_Chaleco",
            "points": [
                [
                    165.61184,
                    150.87680000000003
                ],
                [
                    518.83872,
                    622.91776
                ]
            ],
            "group_id": null,
            "shape_type": "rectangle",
            "flags": {}
        },
        {
            "label": "Sin_Casco_Mascarrilla",
            "points": [
                [
                    458.7008000000001,
                    94.76000000000002
                ],
                [
                    640.0,
                    375.12672
                ]
            ],
            "group_id": null,
            "shape_type": "rectangle",
            "flags": {}
        },
        {
            "label": "Con_Casco",
            "points": [
                [
                    289.84032,
                    0.0
                ],
                [
                    507.8672,
                    222.97728
                ]
            ],
            "group_id": null,
            "shape_type": "rectangle",
            "flags": {}
        }
    ],
    "imagePath": "1675_aug3.jpg",
    "imageData": null,
    "imageHeight": 640,
    "imageWidth": 640
}