{
    "version": "5.0.1",
    "flags": {},
    "shapes": [
        {
            "label": "Con_Casco",
            "points": [
                [
                    153.49984,
                    1.500159999999994
                ],
                [
                    470.50016,
                    358.49984
                ]
            ],
            "group_id": null,
            "shape_type": "rectangle",
            "flags": {}
        }
    ],
    "imagePath": "1677_aug2.jpg",
    "imageData": null,
    "imageHeight": 640,
    "imageWidth": 640
}