{
    "version": "5.0.1",
    "flags": {},
    "shapes": [
        {
            "label": "Sin_Casco_Mascarrilla",
            "points": [
                [
                    33.12256,
                    173.24672
                ],
                [
                    99.71584000000001,
                    273.54112
                ]
            ],
            "group_id": null,
            "shape_type": "rectangle",
            "flags": {}
        },
        {
            "label": "Sin_Casco_Mascarrilla",
            "points": [
                [
                    105.76639999999999,
                    259.74592
                ],
                [
                    162.49856,
                    340.4704
                ]
            ],
            "group_id": null,
            "shape_type": "rectangle",
            "flags": {}
        },
        {
            "label": "Sin_Casco_Mascarrilla",
            "points": [
                [
                    191.65503999999999,
                    222.91647999999998
                ],
                [
                    255.43872,
                    328.56512
                ]
            ],
            "group_id": null,
            "shape_type": "rectangle",
            "flags": {}
        },
        {
            "label": "Sin_Casco_Mascarrilla",
            "points": [
                [
                    272.89504,
                    260.93184
                ],
                [
                    330.59168,
                    349.8816
                ]
            ],
            "group_id": null,
            "shape_type": "rectangle",
            "flags": {}
        },
        {
            "label": "Sin_Casco_Mascarrilla",
            "points": [
                [
                    376.23872,
                    146.79327999999998
                ],
                [
                    462.93824,
                    283.60416
                ]
            ],
            "group_id": null,
            "shape_type": "rectangle",
            "flags": {}
        },
        {
            "label": "Sin_Chaleco",
            "points": [
                [
                    213.79103999999998,
                    359.12447999999995
                ],
                [
                    335.55552,
                    616.93952
                ]
            ],
            "group_id": null,
            "shape_type": "rectangle",
            "flags": {}
        },
        {
            "label": "Sin_Chaleco",
            "points": [
                [
                    71.27071999999998,
                    338.13599999999997
                ],
                [
                    174.14752,
                    502.74208
                ]
            ],
            "group_id": null,
            "shape_type": "rectangle",
            "flags": {}
        },
        {
            "label": "Sin_Chaleco",
            "points": [
                [
                    0.0003200000000020964,
                    259.29568
                ],
                [
                    107.72448,
                    432.19744
                ]
            ],
            "group_id": null,
            "shape_type": "rectangle",
            "flags": {}
        },
        {
            "label": "Sin_Chaleco",
            "points": [
                [
                    324.78592,
                    274.96128
                ],
                [
                    474.32576,
                    597.904
                ]
            ],
            "group_id": null,
            "shape_type": "rectangle",
            "flags": {}
        }
    ],
    "imagePath": "1731_aug3.jpg",
    "imageData": null,
    "imageHeight": 640,
    "imageWidth": 640
}