{
    "version": "5.0.1",
    "flags": {},
    "shapes": [
        {
            "label": "Con_Casco",
            "points": [
                [
                    341.9152,
                    90.28863999999999
                ],
                [
                    451.32000000000005,
                    278.6816
                ]
            ],
            "group_id": null,
            "shape_type": "rectangle",
            "flags": {}
        },
        {
            "label": "Con_Chaleco",
            "points": [
                [
                    254.40448,
                    264.50336
                ],
                [
                    437.45088,
                    592.1392000000001
                ]
            ],
            "group_id": null,
            "shape_type": "rectangle",
            "flags": {}
        }
    ],
    "imagePath": "1749_aug2.jpg",
    "imageData": null,
    "imageHeight": 640,
    "imageWidth": 640
}