{
    "version": "5.0.1",
    "flags": {},
    "shapes": [
        {
            "label": "Sin_Casco_Mascarrilla",
            "points": [
                [
                    258.60704,
                    0.00032000000001630724
                ],
                [
                    625.1472,
                    353.38592000000006
                ]
            ],
            "group_id": null,
            "shape_type": "rectangle",
            "flags": {}
        }
    ],
    "imagePath": "1784_aug3.jpg",
    "imageData": null,
    "imageHeight": 640,
    "imageWidth": 640
}