{
    "version": "5.0.1",
    "flags": {},
    "shapes": [
        {
            "label": "Sin_Casco_Mascarrilla",
            "points": [
                [
                    224.1008,
                    102.11519999999999
                ],
                [
                    314.21088000000003,
                    207.51296
                ]
            ],
            "group_id": null,
            "shape_type": "rectangle",
            "flags": {}
        },
        {
            "label": "Sin_Chaleco",
            "points": [
                [
                    180.9264,
                    199.38367999999997
                ],
                [
                    371.54464,
                    388.66496
                ]
            ],
            "group_id": null,
            "shape_type": "rectangle",
            "flags": {}
        }
    ],
    "imagePath": "1811_aug3.jpg",
    "imageData": null,
    "imageHeight": 640,
    "imageWidth": 640
}