{
    "version": "5.0.1",
    "flags": {},
    "shapes": [
        {
            "label": "Con_Chaleco",
            "points": [
                [
                    434.92640000000006,
                    173.99584
                ],
                [
                    535.73856,
                    379.41856
                ]
            ],
            "group_id": null,
            "shape_type": "rectangle",
            "flags": {}
        },
        {
            "label": "Con_Chaleco",
            "points": [
                [
                    550.7711999999999,
                    179.98592
                ],
                [
                    640.0,
                    395.25504
                ]
            ],
            "group_id": null,
            "shape_type": "rectangle",
            "flags": {}
        },
        {
            "label": "Sin_Chaleco",
            "points": [
                [
                    309.96031999999997,
                    171.31263999999996
                ],
                [
                    403.25696,
                    354.0531199999999
                ]
            ],
            "group_id": null,
            "shape_type": "rectangle",
            "flags": {}
        }
    ],
    "imagePath": "277_aug1.jpg",
    "imageData": null,
    "imageHeight": 640,
    "imageWidth": 640
}