{
    "version": "5.0.1",
    "flags": {},
    "shapes": [
        {
            "label": "Con_Chaleco",
            "points": [
                [
                    152.44864,
                    271.36128
                ],
                [
                    290.61568,
                    518.1235200000001
                ]
            ],
            "group_id": null,
            "shape_type": "rectangle",
            "flags": {}
        },
        {
            "label": "Con_Casco",
            "points": [
                [
                    335.0704,
                    73.75648000000001
                ],
                [
                    409.70912000000004,
                    221.59712000000002
                ]
            ],
            "group_id": null,
            "shape_type": "rectangle",
            "flags": {}
        }
    ],
    "imagePath": "290_aug2.jpg",
    "imageData": null,
    "imageHeight": 640,
    "imageWidth": 640
}