{
    "version": "5.0.1",
    "flags": {},
    "shapes": [
        {
            "label": "Con_Casco",
            "points": [
                [
                    463.50016,
                    256.25023999999996
                ],
                [
                    499.50016,
                    317.7504
                ]
            ],
            "group_id": null,
            "shape_type": "rectangle",
            "flags": {}
        },
        {
            "label": "Con_Casco",
            "points": [
                [
                    341.99968000000007,
                    248.75039999999998
                ],
                [
                    371.00000000000006,
                    301.25023999999996
                ]
            ],
            "group_id": null,
            "shape_type": "rectangle",
            "flags": {}
        }
    ],
    "imagePath": "391_aug2.jpg",
    "imageData": null,
    "imageHeight": 640,
    "imageWidth": 640
}