{
    "version": "5.0.1",
    "flags": {},
    "shapes": [
        {
            "label": "Con_Casco",
            "points": [
                [
                    179.00032000000002,
                    166.99968
                ],
                [
                    300.0,
                    414.0
                ]
            ],
            "group_id": null,
            "shape_type": "rectangle",
            "flags": {}
        }
    ],
    "imagePath": "510_aug3.jpg",
    "imageData": null,
    "imageHeight": 640,
    "imageWidth": 640
}