{
    "version": "5.0.1",
    "flags": {},
    "shapes": [
        {
            "label": "Sin_Chaleco",
            "points": [
                [
                    436.43103999999994,
                    256.18624
                ],
                [
                    602.8752,
                    479.73824
                ]
            ],
            "group_id": null,
            "shape_type": "rectangle",
            "flags": {}
        }
    ],
    "imagePath": "701_aug2.jpg",
    "imageData": null,
    "imageHeight": 640,
    "imageWidth": 640
}