{
    "version": "5.0.1",
    "flags": {},
    "shapes": [
        {
            "label": "Con_Casco",
            "points": [
                [
                    177.49983999999998,
                    233.50048
                ],
                [
                    203.49983999999998,
                    276.50016
                ]
            ],
            "group_id": null,
            "shape_type": "rectangle",
            "flags": {}
        }
    ],
    "imagePath": "766_aug2.jpg",
    "imageData": null,
    "imageHeight": 640,
    "imageWidth": 640
}