{
    "version": "5.0.1",
    "flags": {},
    "shapes": [
        {
            "label": "Con_Chaleco",
            "points": [
                [
                    0.00031999999998788553,
                    414.69856
                ],
                [
                    299.77184,
                    639.99968
                ]
            ],
            "group_id": null,
            "shape_type": "rectangle",
            "flags": {}
        },
        {
            "label": "Con_Chaleco",
            "points": [
                [
                    495.27680000000004,
                    319.22944000000007
                ],
                [
                    640.0,
                    640.0
                ]
            ],
            "group_id": null,
            "shape_type": "rectangle",
            "flags": {}
        },
        {
            "label": "Con_Casco",
            "points": [
                [
                    313.45984,
                    167.03360000000004
                ],
                [
                    465.07583999999997,
                    374.2144
                ]
            ],
            "group_id": null,
            "shape_type": "rectangle",
            "flags": {}
        }
    ],
    "imagePath": "767_aug3.jpg",
    "imageData": null,
    "imageHeight": 640,
    "imageWidth": 640
}