{
    "version": "5.0.1",
    "flags": {},
    "shapes": [
        {
            "label": "Sin_Chaleco",
            "points": [
                [
                    529.4454400000001,
                    193.77408000000003
                ],
                [
                    584.05472,
                    279.25376
                ]
            ],
            "group_id": null,
            "shape_type": "rectangle",
            "flags": {}
        },
        {
            "label": "Sin_Chaleco",
            "points": [
                [
                    318.15583999999996,
                    223.86688
                ],
                [
                    389.75584,
                    326.51136
                ]
            ],
            "group_id": null,
            "shape_type": "rectangle",
            "flags": {}
        },
        {
            "label": "Sin_Casco_Mascarrilla",
            "points": [
                [
                    367.55296,
                    173.96416000000002
                ],
                [
                    395.22848,
                    209.27808000000002
                ]
            ],
            "group_id": null,
            "shape_type": "rectangle",
            "flags": {}
        },
        {
            "label": "Sin_Casco_Mascarrilla",
            "points": [
                [
                    239.00608,
                    200.81824
                ],
                [
                    273.03232,
                    235.56704000000002
                ]
            ],
            "group_id": null,
            "shape_type": "rectangle",
            "flags": {}
        }
    ],
    "imagePath": "781_aug3.jpg",
    "imageData": null,
    "imageHeight": 640,
    "imageWidth": 640
}