{
    "version": "5.0.1",
    "flags": {},
    "shapes": [
        {
            "label": "Con_Casco",
            "points": [
                [
                    257.64128000000005,
                    257.61376
                ],
                [
                    364.34528,
                    348.82464
                ]
            ],
            "group_id": null,
            "shape_type": "rectangle",
            "flags": {}
        },
        {
            "label": "Con_Casco",
            "points": [
                [
                    373.12159999999994,
                    284.33184000000006
                ],
                [
                    478.58912,
                    373.78656
                ]
            ],
            "group_id": null,
            "shape_type": "rectangle",
            "flags": {}
        },
        {
            "label": "Con_Casco",
            "points": [
                [
                    122.84480000000002,
                    258.128
                ],
                [
                    240.90688,
                    340.62272
                ]
            ],
            "group_id": null,
            "shape_type": "rectangle",
            "flags": {}
        }
    ],
    "imagePath": "867_aug1.jpg",
    "imageData": null,
    "imageHeight": 640,
    "imageWidth": 640
}