{
    "version": "5.0.1",
    "flags": {},
    "shapes": [
        {
            "label": "Con_Casco",
            "points": [
                [
                    515.39264,
                    143.50784
                ],
                [
                    587.5756799999999,
                    240.46528
                ]
            ],
            "group_id": null,
            "shape_type": "rectangle",
            "flags": {}
        },
        {
            "label": "Con_Casco",
            "points": [
                [
                    383.02783999999997,
                    162.9072
                ],
                [
                    455.66656,
                    262.87072
                ]
            ],
            "group_id": null,
            "shape_type": "rectangle",
            "flags": {}
        },
        {
            "label": "Sin_Chaleco",
            "points": [
                [
                    67.81855999999998,
                    255.74880000000002
                ],
                [
                    219.27263999999997,
                    447.80064
                ]
            ],
            "group_id": null,
            "shape_type": "rectangle",
            "flags": {}
        }
    ],
    "imagePath": "949_aug3.jpg",
    "imageData": null,
    "imageHeight": 640,
    "imageWidth": 640
}