{
    "version": "5.0.1",
    "flags": {},
    "shapes": [
        {
            "label": "Con_Chaleco",
            "points": [
                [
                    306.14528,
                    278.41216
                ],
                [
                    407.5264,
                    463.8048
                ]
            ],
            "group_id": null,
            "shape_type": "rectangle",
            "flags": {}
        },
        {
            "label": "Con_Chaleco",
            "points": [
                [
                    377.7296,
                    327.49856
                ],
                [
                    484.09695999999997,
                    509.08128
                ]
            ],
            "group_id": null,
            "shape_type": "rectangle",
            "flags": {}
        },
        {
            "label": "Sin_Casco_Mascarrilla",
            "points": [
                [
                    445.0704,
                    256.92608
                ],
                [
                    486.04,
                    326.56832
                ]
            ],
            "group_id": null,
            "shape_type": "rectangle",
            "flags": {}
        },
        {
            "label": "Con_Casco",
            "points": [
                [
                    362.63455999999996,
                    195.69727999999998
                ],
                [
                    416.20192,
                    285.20384
                ]
            ],
            "group_id": null,
            "shape_type": "rectangle",
            "flags": {}
        }
    ],
    "imagePath": "94_aug3.jpg",
    "imageData": null,
    "imageHeight": 640,
    "imageWidth": 640
}