{
    "version": "5.0.1",
    "flags": {},
    "shapes": [
        {
            "label": "Sin_Casco_Mascarrilla",
            "points": [
                [
                    472.7843200000001,
                    151.38304000000002
                ],
                [
                    535.6688,
                    251.44192
                ]
            ],
            "group_id": null,
            "shape_type": "rectangle",
            "flags": {}
        },
        {
            "label": "Sin_Casco_Mascarrilla",
            "points": [
                [
                    346.39296,
                    178.89504
                ],
                [
                    411.27616,
                    286.61792
                ]
            ],
            "group_id": null,
            "shape_type": "rectangle",
            "flags": {}
        },
        {
            "label": "Sin_Casco_Mascarrilla",
            "points": [
                [
                    132.72479999999996,
                    228.68352000000002
                ],
                [
                    192.96735999999999,
                    327.70944000000003
                ]
            ],
            "group_id": null,
            "shape_type": "rectangle",
            "flags": {}
        }
    ],
    "imagePath": "960_aug3.jpg",
    "imageData": null,
    "imageHeight": 640,
    "imageWidth": 640
}