{
    "version": "5.0.1",
    "flags": {},
    "shapes": [
        {
            "label": "Sin_Chaleco",
            "points": [
                [
                    286.92096,
                    277.6752
                ],
                [
                    331.60319999999996,
                    369.60928
                ]
            ],
            "group_id": null,
            "shape_type": "rectangle",
            "flags": {}
        },
        {
            "label": "Sin_Chaleco",
            "points": [
                [
                    211.07968,
                    279.03455999999994
                ],
                [
                    254.9312,
                    374.4656
                ]
            ],
            "group_id": null,
            "shape_type": "rectangle",
            "flags": {}
        },
        {
            "label": "Con_Casco",
            "points": [
                [
                    467.34624,
                    234.09344000000002
                ],
                [
                    491.128,
                    280.69568000000004
                ]
            ],
            "group_id": null,
            "shape_type": "rectangle",
            "flags": {}
        },
        {
            "label": "Con_Casco",
            "points": [
                [
                    119.42943999999999,
                    204.14368
                ],
                [
                    150.66719999999998,
                    261.56512
                ]
            ],
            "group_id": null,
            "shape_type": "rectangle",
            "flags": {}
        }
    ],
    "imagePath": "975_aug3.jpg",
    "imageData": null,
    "imageHeight": 640,
    "imageWidth": 640
}