{
    "version": "5.0.1",
    "flags": {},
    "shapes": [
        {
            "label": "Con_Mascarrilla",
            "points": [
                [
                    142.00006100000002,
                    344.20000000000005
                ],
                [
                    225.00020899999998,
                    387.0
                ]
            ],
            "group_id": null,
            "shape_type": "rectangle",
            "flags": {}
        }
    ],
    "imagePath": "maksssksksss485.png",
    "imageData": null,
    "imageHeight": 400,
    "imageWidth": 301
}