{
    "version": "5.0.1",
    "flags": {},
    "shapes": [
        {
            "label": "Con_Mascarrilla",
            "points": [
                [
                    1.0,
                    89.600056
                ],
                [
                    81.0,
                    135.999864
                ]
            ],
            "group_id": null,
            "shape_type": "rectangle",
            "flags": {}
        },
        {
            "label": "Con_Mascarrilla",
            "points": [
                [
                    151.0,
                    158.599896
                ],
                [
                    247.0,
                    204.999704
                ]
            ],
            "group_id": null,
            "shape_type": "rectangle",
            "flags": {}
        },
        {
            "label": "Con_Mascarrilla",
            "points": [
                [
                    243.0,
                    155.39979
                ],
                [
                    283.0,
                    178.99973
                ]
            ],
            "group_id": null,
            "shape_type": "rectangle",
            "flags": {}
        }
    ],
    "imagePath": "maksssksksss148.png",
    "imageData": null,
    "imageHeight": 364,
    "imageWidth": 400
}